pydlr/__init__.py
pydlr/kernel.py
pydlr/kernel_fortran.py
pydlr/pydlr.py
pydlr/utils.py
pydlr-1.0.1.dist-info/LICENSE
pydlr-1.0.1.dist-info/METADATA
pydlr-1.0.1.dist-info/WHEEL
pydlr-1.0.1.dist-info/top_level.txt
pydlr-1.0.1.dist-info/RECORD
