Metadata-Version: 2.1
Name: pydlr
Version: 1.0.1
Summary: Discrete Lehmann Representation for imaginary time calculations
Home-page: https://github.com/jasonkaye/libdlr
Author: Hugo U.R. Strand
Author-email: hugo.strand@gmail.com
Project-URL: Documentation, https://libdlr.readthedocs.io
Classifier: Programming Language :: Python :: 3
Classifier: License :: OSI Approved :: Apache Software License
Classifier: Operating System :: OS Independent
Classifier: Topic :: Scientific/Engineering :: Physics
Classifier: Topic :: Scientific/Engineering :: Chemistry
Classifier: Intended Audience :: Science/Research
Requires-Python: >=3.6
License-File: LICENSE
